.gitignore
Artifactory.py
Dockerfile
README.md
requirements.txt
setup.cfg
setup.py
test_Artifactory.py
.buildkite/deploy.sh
.buildkite/pipeline.sh
artifactory_lib.egg-info/PKG-INFO
artifactory_lib.egg-info/SOURCES.txt
artifactory_lib.egg-info/dependency_links.txt
artifactory_lib.egg-info/requires.txt
artifactory_lib.egg-info/top_level.txt