Metadata-Version: 1.1
Name: artifactory-lib
Version: 0.0.12
Summary: Python library for interacting with Artifactory API
Home-page: https://github.com/MYOB-Technology/artifactory-lib
Author: Gustavo Hoirisch
Author-email: gustavo.hoirisch@myob.com
License: MIT
Keywords: artifactory management library
Platform: UNKNOWN
Classifier: Development Status :: 3 - Alpha
Classifier: Intended Audience :: Developers
Classifier: Topic :: Software Development :: Build Tools
Classifier: License :: OSI Approved :: MIT License
Classifier: Programming Language :: Python :: 2
Classifier: Programming Language :: Python :: 2.7
